sigma/backends/quickwit/__init__.py
sigma/backends/quickwit/quickwit.py
sigma/pipelines/quickwit/__init__.py
sigma/pipelines/quickwit/quickwit.py
pysigma_backend_quickwit-0.1.4.dist-info/METADATA
pysigma_backend_quickwit-0.1.4.dist-info/WHEEL
pysigma_backend_quickwit-0.1.4.dist-info/licenses/LICENSE
pysigma_backend_quickwit-0.1.4.dist-info/RECORD
