Metadata-Version: 2.4
Name: pySigma-backend-quickwit
Version: 0.1.4
Summary: pySigma Quickwit backend
License: MIT
License-File: LICENSE
Author: Alex Sinnott
Author-email: alex@sinn.io
Requires-Python: >=3.9,<4.0
Classifier: License :: OSI Approved :: MIT License
Classifier: Programming Language :: Python :: 3
Classifier: Programming Language :: Python :: 3.9
Classifier: Programming Language :: Python :: 3.10
Classifier: Programming Language :: Python :: 3.11
Classifier: Programming Language :: Python :: 3.12
Classifier: Programming Language :: Python :: 3.13
Classifier: Programming Language :: Python :: 3.14
Requires-Dist: pysigma (>0.11.16,<2)
Project-URL: Repository, https://github.com/sifex/pySigma-backend-quickwit
